devwatch/__main__.py
devwatch/devwatch.py
devwatch-0.0.6.data/scripts/devwatch
devwatch-0.0.6.dist-info/LICENSE
devwatch-0.0.6.dist-info/METADATA
devwatch-0.0.6.dist-info/WHEEL
devwatch-0.0.6.dist-info/top_level.txt
devwatch-0.0.6.dist-info/RECORD
