Metadata-Version: 2.1
Name: devwatch
Version: 0.0.6
Summary: Speed up your coding by running a command on every saved change
Home-page: https://github.com/ulisesojeda/devwatch
Author: Ulises Ojeda
License: LICENSE
Platform: UNKNOWN
Requires-Python: >=3.2
Requires-Dist: pyyaml
